Workbook

Sheet Instructions
A1: EXCEL DASHBOARD PROJECT — INSTRUCTIONS
A3: Sr. No. | B3: Task Description | C3: How to Complete | D3: Status
A4: 1 | B4: Time Limit: 3 hours | C4: Complete tasks in the listed order. | D4: Ready
A5: 2 | B5: Choose any dataset from Kaggle/UCI ML Repository | C5: This workbook uses a sample Retail Sales dataset for practice. Replace it with an approved Kaggle/UCI dataset if required. | D5: Ready
A6: 3 | B6: Create an interactive dashboard | C6: Use Dashboard filters for Region and Category; KPI cards and charts update based on the selected filters. | D6: Ready
A7: 4 | B7: Complete tasks in order listed | C7: Follow the Tasks sheet from data import through documentation. | D7: Ready
A8: 5 | B8: Save work every 15 minutes | C8: Press Ctrl+S regularly while working. | D8: Reminder
A9: 6 | B9: Submit final file as 'YourName_ExcelDashboard.xlsx' | C9: Rename this file using your name before submitting. | D9: Rename before submission

Sheet Tasks
A1: TASK PLAN & SKILLS CHECKLIST
A3: Sr. No. | B3: Task Description | C3: Skills Tested | D3: Time Estimate Min | E3: Weightage
A4: 1 | B4: Dataset Selection & Import | C4: Data Import, Initial Cleaning | D4: 15 | E4: 0.05
A5: 2 | B5: Data Cleaning & Preparation | C5: Remove duplicates, Handle missing values, Format data types | D5: 25 | E5: 0.1
A6: 3 | B6: Create Pivot Tables | C6: Data Analysis, Summarization | D6: 30 | E6: 0.15
A7: 4 | B7: Advanced Formulas | C7: VLOOKUP, INDEX-MATCH, IF conditions, nested functions | D7: 35 | E7: 0.15
A8: 5 | B8: Data Visualization | C8: Charts, Conditional Formatting | D8: 40 | E8: 0.2
A9: 6 | B9: Interactive Dashboard | C9: Slicers, Timeline, Dynamic ranges; dropdown filters used in this workbook | D9: 45 | E9: 0.25
A10: 7 | B10: Documentation | C10: Sheet organization, Naming conventions, Instructions | D10: 20 | E10: 0.1
C12: Total time (minutes) | D12: =SUM(D4:D10) -> 210
C13: Total weightage | E13: =SUM(E4:E10) -> 1

Sheet Raw Data
A1: Order ID | B1: Order Date | C1: Region | D1: Category | E1: Product | F1: Units | G1: Unit Price | H1: Sales | I1: Cost | J1: Profit | K1: Salesperson | L1: Customer Type
A2: ORD0001 | B2: 45710 | C2: South | D2: Office Supplies | E2: Notebook | F2: 1 | G2: 5.29 | H2: 5.29 | I2: 3.14 | J2: 2.15 | K2: Jay | L2: New
A3: ORD0002 | B3: 45945 | C3: North | D3: Office Supplies | E3: Stapler | F3: 1 | G3: 8.87 | H3: 8.87 | I3: 5.19 | J3: 3.68 | K3: Ravi | L3: Business
A4: ORD0003 | B4: 45739 | C4: North | D4: Office Supplies | E4: Stapler | F4: 4 | G4: 9.88 | H4: 39.52 | I4: 23.85 | J4: 15.67 | K4: Kiran | L4: Returning
A5: ORD0004 | B5: 45852 | C5: North | D5: Furniture | E5: Chair | F5: 4 | G5: 105.42 | H5: 421.68 | I5: 261.85 | J5: 159.83 | K5: Asha | L5: Returning
A6: ORD0005 | B6: 45851 | C6: North | D6: Furniture | E6: Bookshelf | F6: 13 | G6: 124.66 | H6: 1620.58 | I6: 1066.06 | J6: 554.52 | K6: Asha | L6: Business
A7: ORD0006 | B7: 45806 | C7: South | D7: Furniture | E7: Bookshelf | F7: 10 | G7: 129.66 | H7: 1296.6 | I7: 701.29 | J7: 595.31 | K7: Asha | L7: New
A8: ORD0007 | B8: 45847 | C8: South | D8: Electronics | E8: Keyboard | F8: 5 | G8: 34.61 | H8: 173.05 | I8: 133.29 | J8: 39.76 | K8: Neha | L8: New
A9: ORD0008 | B9: 45931 | C9: South | D9: Office Supplies | E9: Printer Paper | F9: 12 | G9: 8.84 | H9: 106.08 | I9: 75.78 | J9: 30.3 | K9: Ravi | L9: New
A10: ORD0009 | B10: 46008 | C10: South | D10: Furniture | E10: Cabinet | F10: 5 | G10: 178.8 | H10: 894 | I10: 636.53 | J10: 257.47 | K10: Neha | L10: New
A11: ORD0010 | B11: 45948 | C11: South | D11: Electronics | E11: Laptop | F11: 13 | G11: 621.21 | H11: 8075.73 | I11: 4848.04 | J11: 3227.69 | K11: Neha | L11: New
A12: ORD0011 | B12: 45793 | C12: South | D12: Office Supplies | E12: Stapler | F12: 7 | G12: 10.92 | H12: 76.44 | I12: 54.49 | J12: 21.95 | K12: Ravi | L12: New
A13: ORD0012 | B13: 45843 | C13: West | D13: Office Supplies | E13: Printer Paper | F13: 12 | G13: 8.16 | H13: 97.92 | I13: 77.29 | J13: 20.63 | K13: Ravi | L13: New
... A17: ORD0016 | B17: 45914 | C17: East | D17: Electronics | E17: Keyboard | F17: 1 | G17: 38.81 | H17: 38.81 | I17: 30.38 | J17: 8.43 | K17: Ravi | L17: Business
A18: ORD0017 | B18: 45849 | C18: South | D18: Electronics | E18: Monitor | F18: 14 | G18: 227.34 | H18: 3182.76 | I18: 2236.5 | J18: 946.26 | L18: Business
A19: ORD0018 | B19: 45815 | C19: East | D19: Office Supplies | E19: Notebook | F19: 10 | G19: 4.79 | H19: 47.9 | I19: 25.19 | J19: 22.71 | K19: Ravi | L19: New
A20: ORD0019 | B20: 45723 | C20: South | D20: Electronics | E20: Laptop | F20: 2 | G20: 686.18 | H20: 1372.36 | I20: 1049.59 | J20: 322.77 | K20: Kiran | L20: Business
A21: ORD0020 | B21: 45934 | C21: South | D21: Electronics | E21: Monitor | F21: 9 | G21: 239.66 | H21: 2156.94 | I21: 1395.41 | J21: 761.53 | K21: Ravi | L21: Business
A22: ORD0021 | B22: 45719 | C22: West | D22: Furniture | E22: Cabinet | F22: 11 | G22: 165.76 | H22: 1823.36 | I22: 1187.79 | J22: 635.57 | K22: Ravi | L22: New
A23: ORD0022 | B23: 45661 | C23: South | D23: Electronics | E23: Monitor | F23: 1 | G23: 224.66 | H23: 224.66 | I23: 132.33 | J23: 92.33 | K23: Asha | L23: Business
A24: ORD0023 | B24: 45694 | C24: East | D24: Office Supplies | E24: Notebook | F24: 4 | G24: 4.48 | H24: 17.92 | I24: 9.49 | J24: 8.43 | K24: Jay | L24: New
A25: ORD0024 | B25: 45782 | C25: West | D25: Furniture | E25: Cabinet | G25: 161.51 | H25: 646.04 | I25: 476.14 | J25: 169.9 | K25: Kiran | L25: Returning
A26: ORD0025 | B26: 45897 | C26: West | D26: Electronics | E26: Laptop | F26: 2 | G26: 674.8 | H26: 1349.6 | I26: 845.24 | J26: 504.36 | K26: Asha | L26: Business
A27: ORD0026 | B27: 45785 | C27: North | D27: Office Supplies | E27: Notebook | F27: 1 | G27: 4.88 | H27: 4.88 | I27: 3.03 | J27: 1.85 | K27: Ravi | L27: New
A28: ORD0027 | B28: 45696 | C28: South | D28: Office Supplies | E28: Stapler | F28: 3 | G28: 9.81 | H28: 29.43 | I28: 17.76 | J28: 11.67 | K28: Kiran | L28: Business
A29: ORD0028 | B29: 45779 | C29: North | D29: Electronics | E29: Laptop | F29: 11 | G29: 727.89 | H29: 8006.79 | I29: 6171.7 | J29: 1835.09 | K29: Ravi | L29: Returning
A30: ORD0029 | B30: 45852 | C30: South | D30: Furniture | E30: Cabinet | F30: 4 | G30: 174 | H30: 696 | I30: 550.35 | J30: 145.65 | K30: Asha | L30: Returning
A31: ORD0030 | B31: 45737 | C31: West | D31: Furniture | E31: Cabinet | F31: 5 | G31: 157.04 | H31: 785.2 | I31: 633.81 | J31: 151.39 | K31: Ravi | L31: Returning
A32: ORD0031 | B32: 45687 | C32: East | D32: Electronics | E32: Laptop | F32: 10 | G32: 686.77 | H32: 6867.7 | I32: 3696.8 | J32: 3170.9 | K32: Asha | L32: Business
A33: ORD0032 | B33: 45693 | C33: South | D33: Furniture | E33: Chair | F33: 1 | G33: 105.51 | H33: 105.51 | I33: 57.4 | J33: 48.11 | K33: Jay | L33: New
A34: ORD0033 | B34: 45954 | C34: South | D34: Office Supplies | E34: Pen Set | F34: 7 | G34: 10.91 | H34: 76.37 | I34: 60.11 | J34: 16.26 | K34: Jay | L34: New
A35: ORD0034 | B35: 45791 | C35: East | D35: Office Supplies | E35: Notebook | F35: 7 | G35: 5.19 | H35: 36.33 | I35: 25.05 | J35: 11.28 | K35: Ravi | L35: Business
A36: ORD0035 | B36: 45892 | C36: East | D36: Office Supplies | E36: Printer Paper | F36: 4 | G36: 7.55 | H36: 30.2 | I36: 16.89 | J36: 13.31 | K36: Neha | L36: New
A37: ORD0036 | B37: 45933 | C37: North | D37: Electronics | E37: Keyboard | F37: 10 | G37: 39.19 | H37: 391.9 | I37: 320.9 | J37: 71 | K37: Ravi | L37: Business
... A122: ORD0004 | B122: 45852 | C122: North | D122: Furniture | E122: Chair | F122: 4 | G122: 105.42 | H122: 421.68 | I122: 261.85 | J122: 159.83 | K122: Asha | L122: Returning

Sheet Clean Data
A1: Order ID | B1: Order Date | C1: Region | D1: Category | E1: Product | F1: Units | G1: Unit Price | H1: Sales | I1: Cost | J1: Profit | K1: Salesperson | L1: Customer Type
A2: ='Raw Data'!A2 -> ORD0001 | B2: ='Raw Data'!B2 -> 45710 | C2: ='Raw Data'!C2 -> South | D2: ='Raw Data'!D2 -> Office Supplies | E2: ='Raw Data'!E2 -> Notebook | F2: =IF('Raw Data'!F2="",0,'Raw Data'!F2) -> 1 | G2: ='Raw Data'!G2 -> 5.29 | H2: =F2*G2 -> 5.29 | I2: ='Raw Data'!I2 -> 3.14 | J2: =H2-I2 -> 2.15 | K2: =IF('Raw Data'!K2="","Unknown",'Raw Data'!K2) -> Jay | L2: ='Raw Data'!L2 -> New
A3: ='Raw Data'!A3 -> ORD0002 | B3: ='Raw Data'!B3 -> 45945 | C3: ='Raw Data'!C3 -> North | D3: ='Raw Data'!D3 -> Office Supplies | E3: ='Raw Data'!E3 -> Stapler | F3: =IF('Raw Data'!F3="",0,'Raw Data'!F3) -> 1 | G3: ='Raw Data'!G3 -> 8.87 | H3: =F3*G3 -> 8.87 | I3: ='Raw Data'!I3 -> 5.19 | J3: =H3-I3 -> 3.68 | K3: =IF('Raw Data'!K3="","Unknown",'Raw Data'!K3) -> Ravi | L3: ='Raw Data'!L3 -> Business
A4: ='Raw Data'!A4 -> ORD0003 | B4: ='Raw Data'!B4 -> 45739 | C4: ='Raw Data'!C4 -> North | D4: ='Raw Data'!D4 -> Office Supplies | E4: ='Raw Data'!E4 -> Stapler | F4: =IF('Raw Data'!F4="",0,'Raw Data'!F4) -> 4 | G4: ='Raw Data'!G4 -> 9.88 | H4: =F4*G4 -> 39.52 | I4: ='Raw Data'!I4 -> 23.85 | J4: =H4-I4 -> 15.67 | K4: =IF('Raw Data'!K4="","Unknown",'Raw Data'!K4) -> Kiran | L4: ='Raw Data'!L4 -> Returning
A5: ='Raw Data'!A5 -> ORD0004 | B5: ='Raw Data'!B5 -> 45852 | C5: ='Raw Data'!C5 -> North | D5: ='Raw Data'!D5 -> Furniture | E5: ='Raw Data'!E5 -> Chair | F5: =IF('Raw Data'!F5="",0,'Raw Data'!F5) -> 4 | G5: ='Raw Data'!G5 -> 105.42 | H5: =F5*G5 -> 421.68 | I5: ='Raw Data'!I5 -> 261.85 | J5: =H5-I5 -> 159.83 | K5: =IF('Raw Data'!K5="","Unknown",'Raw Data'!K5) -> Asha | L5: ='Raw Data'!L5 -> Returning
A6: ='Raw Data'!A6 -> ORD0005 | B6: ='Raw Data'!B6 -> 45851 | C6: ='Raw Data'!C6 -> North | D6: ='Raw Data'!D6 -> Furniture | E6: ='Raw Data'!E6 -> Bookshelf | F6: =IF('Raw Data'!F6="",0,'Raw Data'!F6) -> 13 | G6: ='Raw Data'!G6 -> 124.66 | H6: =F6*G6 -> 1620.58 | I6: ='Raw Data'!I6 -> 1066.06 | J6: =H6-I6 -> 554.52 | K6: =IF('Raw Data'!K6="","Unknown",'Raw Data'!K6) -> Asha | L6: ='Raw Data'!L6 -> Business
A7: ='Raw Data'!A7 -> ORD0006 | B7: ='Raw Data'!B7 -> 45806 | C7: ='Raw Data'!C7 -> South | D7: ='Raw Data'!D7 -> Furniture | E7: ='Raw Data'!E7 -> Bookshelf | F7: =IF('Raw Data'!F7="",0,'Raw Data'!F7) -> 10 | G7: ='Raw Data'!G7 -> 129.66 | H7: =F7*G7 -> 1296.6 | I7: ='Raw Data'!I7 -> 701.29 | J7: =H7-I7 -> 595.31 | K7: =IF('Raw Data'!K7="","Unknown",'Raw Data'!K7) -> Asha | L7: ='Raw Data'!L7 -> New
A8: ='Raw Data'!A8 -> ORD0007 | B8: ='Raw Data'!B8 -> 45847 | C8: ='Raw Data'!C8 -> South | D8: ='Raw Data'!D8 -> Electronics | E8: ='Raw Data'!E8 -> Keyboard | F8: =IF('Raw Data'!F8="",0,'Raw Data'!F8) -> 5 | G8: ='Raw Data'!G8 -> 34.61 | H8: =F8*G8 -> 173.05 | I8: ='Raw Data'!I8 -> 133.29 | J8: =H8-I8 -> 39.76 | K8: =IF('Raw Data'!K8="","Unknown",'Raw Data'!K8) -> Neha | L8: ='Raw Data'!L8 -> New
A9: ='Raw Data'!A9 -> ORD0008 | B9: ='Raw Data'!B9 -> 45931 | C9: ='Raw Data'!C9 -> South | D9: ='Raw Data'!D9 -> Office Supplies | E9: ='Raw Data'!E9 -> Printer Paper | F9: =IF('Raw Data'!F9="",0,'Raw Data'!F9) -> 12 | G9: ='Raw Data'!G9 -> 8.84 | H9: =F9*G9 -> 106.08 | I9: ='Raw Data'!I9 -> 75.78 | J9: =H9-I9 -> 30.3 | K9: =IF('Raw Data'!K9="","Unknown",'Raw Data'!K9) -> Ravi | L9: ='Raw Data'!L9 -> New
A10: ='Raw Data'!A10 -> ORD0009 | B10: ='Raw Data'!B10 -> 46008 | C10: ='Raw Data'!C10 -> South | D10: ='Raw Data'!D10 -> Furniture | E10: ='Raw Data'!E10 -> Cabinet | F10: =IF('Raw Data'!F10="",0,'Raw Data'!F10) -> 5 | G10: ='Raw Data'!G10 -> 178.8 | H10: =F10*G10 -> 894 | I10: ='Raw Data'!I10 -> 636.53 | J10: =H10-I10 -> 257.47 | K10: =IF('Raw Data'!K10="","Unknown",'Raw Data'!K10) -> Neha | L10: ='Raw Data'!L10 -> New
A11: ='Raw Data'!A11 -> ORD0010 | B11: ='Raw Data'!B11 -> 45948 | C11: ='Raw Data'!C11 -> South | D11: ='Raw Data'!D11 -> Electronics | E11: ='Raw Data'!E11 -> Laptop | F11: =IF('Raw Data'!F11="",0,'Raw Data'!F11) -> 13 | G11: ='Raw Data'!G11 -> 621.21 | H11: =F11*G11 -> 8075.73 | I11: ='Raw Data'!I11 -> 4848.04 | J11: =H11-I11 -> 3227.69 | K11: =IF('Raw Data'!K11="","Unknown",'Raw Data'!K11) -> Neha | L11: ='Raw Data'!L11 -> New
A12: ='Raw Data'!A12 -> ORD0011 | B12: ='Raw Data'!B12 -> 45793 | C12: ='Raw Data'!C12 -> South | D12: ='Raw Data'!D12 -> Office Supplies | E12: ='Raw Data'!E12 -> Stapler | F12: =IF('Raw Data'!F12="",0,'Raw Data'!F12) -> 7 | G12: ='Raw Data'!G12 -> 10.92 | H12: =F12*G12 -> 76.44 | I12: ='Raw Data'!I12 -> 54.49 | J12: =H12-I12 -> 21.95 | K12: =IF('Raw Data'!K12="","Unknown",'Raw Data'!K12) -> Ravi | L12: ='Raw Data'!L12 -> New
A13: ='Raw Data'!A13 -> ORD0012 | B13: ='Raw Data'!B13 -> 45843 | C13: ='Raw Data'!C13 -> West | D13: ='Raw Data'!D13 -> Office Supplies | E13: ='Raw Data'!E13 -> Printer Paper | F13: =IF('Raw Data'!F13="",0,'Raw Data'!F13) -> 12 | G13: ='Raw Data'!G13 -> 8.16 | H13: =F13*G13 -> 97.92 | I13: ='Raw Data'!I13 -> 77.29 | J13: =H13-I13 -> 20.63 | K13: =IF('Raw Data'!K13="","Unknown",'Raw Data'!K13) -> Ravi | L13: ='Raw Data'!L13 -> New
... A121: ='Raw Data'!A121 -> ORD0120 | B121: ='Raw Data'!B121 -> 45912 | C121: ='Raw Data'!C121 -> South | D121: ='Raw Data'!D121 -> Electronics | E121: ='Raw Data'!E121 -> Laptop | F121: =IF('Raw Data'!F121="",0,'Raw Data'!F121) -> 10 | G121: ='Raw Data'!G121 -> 707.85 | H121: =F121*G121 -> 7078.5 | I121: ='Raw Data'!I121 -> 4996.81 | J121: =H121-I121 -> 2081.69 | K121: =IF('Raw Data'!K121="","Unknown",'Raw Data'!K121) -> Jay | L121: ='Raw Data'!L121 -> New

Sheet Analysis
A1: ANALYSIS & PIVOT-STYLE SUMMARY TABLES
A3: Sales by Region | F3: Sales by Category
A4: Region | B4: Total Sales | C4: Total Profit | D4: Orders | F4: Category | G4: Total Sales | H4: Total Profit
A5: North | B5: =SUMIF('Clean Data'!$C$2:$C$121,A5,'Clean Data'!$H$2:$H$121) -> 32981.26 | C5: =SUMIF('Clean Data'!$C$2:$C$121,A5,'Clean Data'!$J$2:$J$121) -> 10259.4 | D5: =COUNTIF('Clean Data'!$C$2:$C$121,A5) -> 27 | F5: Electronics | G5: =SUMIF('Clean Data'!$D$2:$D$121,F5,'Clean Data'!$H$2:$H$121) -> 84037.89 | H5: =SUMIF('Clean Data'!$D$2:$D$121,F5,'Clean Data'!$J$2:$J$121) -> 27714.43
A6: South | B6: =SUMIF('Clean Data'!$C$2:$C$121,A6,'Clean Data'!$H$2:$H$121) -> 44165.54 | C6: =SUMIF('Clean Data'!$C$2:$C$121,A6,'Clean Data'!$J$2:$J$121) -> 15047.12 | D6: =COUNTIF('Clean Data'!$C$2:$C$121,A6) -> 38 | F6: Furniture | G6: =SUMIF('Clean Data'!$D$2:$D$121,F6,'Clean Data'!$H$2:$H$121) -> 40857.3 | H6: =SUMIF('Clean Data'!$D$2:$D$121,F6,'Clean Data'!$J$2:$J$121) -> 13160.06
A7: East | B7: =SUMIF('Clean Data'!$C$2:$C$121,A7,'Clean Data'!$H$2:$H$121) -> 20943.76 | C7: =SUMIF('Clean Data'!$C$2:$C$121,A7,'Clean Data'!$J$2:$J$121) -> 7399.18 | D7: =COUNTIF('Clean Data'!$C$2:$C$121,A7) -> 30 | F7: Office Supplies | G7: =SUMIF('Clean Data'!$D$2:$D$121,F7,'Clean Data'!$H$2:$H$121) -> 2731.66 | H7: =SUMIF('Clean Data'!$D$2:$D$121,F7,'Clean Data'!$J$2:$J$121) -> 856.91
A8: West | B8: =SUMIF('Clean Data'!$C$2:$C$121,A8,'Clean Data'!$H$2:$H$121) -> 29536.29 | C8: =SUMIF('Clean Data'!$C$2:$C$121,A8,'Clean Data'!$J$2:$J$121) -> 9025.7 | D8: =COUNTIF('Clean Data'!$C$2:$C$121,A8) -> 25
A11: Monthly Sales
A12: Month | B12: Sales | C12: Profit
A13: 45658 | B13: =SUMIFS('Clean Data'!$H$2:$H$121,'Clean Data'!$B$2:$B$121,">="&A13,'Clean Data'!$B$2:$B$121,"<"&EDATE(A13,1)) -> 7969.55 | C13: =SUMIFS('Clean Data'!$J$2:$J$121,'Clean Data'!$B$2:$B$121,">="&A13,'Clean Data'!$B$2:$B$121,"<"&EDATE(A13,1)) -> 3576.29
A14: 45689 | B14: =SUMIFS('Clean Data'!$H$2:$H$121,'Clean Data'!$B$2:$B$121,">="&A14,'Clean Data'!$B$2:$B$121,"<"&EDATE(A14,1)) -> 7052.56 | C14: =SUMIFS('Clean Data'!$J$2:$J$121,'Clean Data'!$B$2:$B$121,">="&A14,'Clean Data'!$B$2:$B$121,"<"&EDATE(A14,1)) -> 2085.15
A15: 45717 | B15: =SUMIFS('Clean Data'!$H$2:$H$121,'Clean Data'!$B$2:$B$121,">="&A15,'Clean Data'!$B$2:$B$121,"<"&EDATE(A15,1)) -> 17832.54 | C15: =SUMIFS('Clean Data'!$J$2:$J$121,'Clean Data'!$B$2:$B$121,">="&A15,'Clean Data'!$B$2:$B$121,"<"&EDATE(A15,1)) -> 5418.96
A16: 45748 | B16: =SUMIFS('Clean Data'!$H$2:$H$121,'Clean Data'!$B$2:$B$121,">="&A16,'Clean Data'!$B$2:$B$121,"<"&EDATE(A16,1)) -> 718.97 | C16: =SUMIFS('Clean Data'!$J$2:$J$121,'Clean Data'!$B$2:$B$121,">="&A16,'Clean Data'!$B$2:$B$121,"<"&EDATE(A16,1)) -> 250.98
A17: 45778 | B17: =SUMIFS('Clean Data'!$H$2:$H$121,'Clean Data'!$B$2:$B$121,">="&A17,'Clean Data'!$B$2:$B$121,"<"&EDATE(A17,1)) -> 17501.33 | C17: =SUMIFS('Clean Data'!$J$2:$J$121,'Clean Data'!$B$2:$B$121,">="&A17,'Clean Data'!$B$2:$B$121,"<"&EDATE(A17,1)) -> 5110.57
A18: 45809 | B18: =SUMIFS('Clean Data'!$H$2:$H$121,'Clean Data'!$B$2:$B$121,">="&A18,'Clean Data'!$B$2:$B$121,"<"&EDATE(A18,1)) -> 9697.06 | C18: =SUMIFS('Clean Data'!$J$2:$J$121,'Clean Data'!$B$2:$B$121,">="&A18,'Clean Data'!$B$2:$B$121,"<"&EDATE(A18,1)) -> 3751.09
A19: 45839 | B19: =SUMIFS('Clean Data'!$H$2:$H$121,'Clean Data'!$B$2:$B$121,">="&A19,'Clean Data'!$B$2:$B$121,"<"&EDATE(A19,1)) -> 10990.94 | C19: =SUMIFS('Clean Data'!$J$2:$J$121,'Clean Data'!$B$2:$B$121,">="&A19,'Clean Data'!$B$2:$B$121,"<"&EDATE(A19,1)) -> 3457.29
A20: 45870 | B20: =SUMIFS('Clean Data'!$H$2:$H$121,'Clean Data'!$B$2:$B$121,">="&A20,'Clean Data'!$B$2:$B$121,"<"&EDATE(A20,1)) -> 6177.73 | C20: =SUMIFS('Clean Data'!$J$2:$J$121,'Clean Data'!$B$2:$B$121,">="&A20,'Clean Data'!$B$2:$B$121,"<"&EDATE(A20,1)) -> 1981.92
A21: 45901 | B21: =SUMIFS('Clean Data'!$H$2:$H$121,'Clean Data'!$B$2:$B$121,">="&A21,'Clean Data'!$B$2:$B$121,"<"&EDATE(A21,1)) -> 17785.22 | C21: =SUMIFS('Clean Data'!$J$2:$J$121,'Clean Data'!$B$2:$B$121,">="&A21,'Clean Data'!$B$2:$B$121,"<"&EDATE(A21,1)) -> 5235.84
A22: 45931 | B22: =SUMIFS('Clean Data'!$H$2:$H$121,'Clean Data'!$B$2:$B$121,">="&A22,'Clean Data'!$B$2:$B$121,"<"&EDATE(A22,1)) -> 18951.1 | C22: =SUMIFS('Clean Data'!$J$2:$J$121,'Clean Data'!$B$2:$B$121,">="&A22,'Clean Data'!$B$2:$B$121,"<"&EDATE(A22,1)) -> 6491.8
A23: 45962 | B23: =SUMIFS('Clean Data'!$H$2:$H$121,'Clean Data'!$B$2:$B$121,">="&A23,'Clean Data'!$B$2:$B$121,"<"&EDATE(A23,1)) -> 5204.49 | C23: =SUMIFS('Clean Data'!$J$2:$J$121,'Clean Data'!$B$2:$B$121,">="&A23,'Clean Data'!$B$2:$B$121,"<"&EDATE(A23,1)) -> 1960.17
A24: 45992 | B24: =SUMIFS('Clean Data'!$H$2:$H$121,'Clean Data'!$B$2:$B$121,">="&A24,'Clean Data'!$B$2:$B$121,"<"&EDATE(A24,1)) -> 7745.36 | C24: =SUMIFS('Clean Data'!$J$2:$J$121,'Clean Data'!$B$2:$B$121,">="&A24,'Clean Data'!$B$2:$B$121,"<"&EDATE(A24,1)) -> 2411.34

Sheet Dashboard
A1: RETAIL SALES INTERACTIVE DASHBOARD
A3: Region Filter | B3: All | D3: Category Filter | E3: All
A4: Change the dropdowns to filter KPI totals. Charts below show overall summaries; use Analysis for region/category detail.
A6: Total Sales | D6: Total Profit | G6: Units Sold
A7: =SUMPRODUCT((IF($B$3="All",1,'Clean Data'!$C$2:$C$121=$B$3))*(IF($E$3="All",1,'Clean Data'!$D$2:$D$121=$E$3))*'Clean Data'!$H$2:$H$121) -> 127626.85 | D7: =SUMPRODUCT((IF($B$3="All",1,'Clean Data'!$C$2:$C$121=$B$3))*(IF($E$3="All",1,'Clean Data'!$D$2:$D$121=$E$3))*'Clean Data'!$J$2:$J$121) -> 41731.4 | G7: =SUMPRODUCT((IF($B$3="All",1,'Clean Data'!$C$2:$C$121=$B$3))*(IF($E$3="All",1,'Clean Data'!$D$2:$D$121=$E$3))*'Clean Data'!$F$2:$F$121) -> 920

Sheet Documentation
A1: DOCUMENTATION & FORMULA GUIDE
A3: Area | B3: What is included | C3: Formula / method | D3: Notes
A4: Dataset | B4: Retail sales practice data, 120 records | C4: Generated sample dataset | D4: Use a Kaggle/UCI dataset if your instructor requires a published dataset.
A5: Cleaning | B5: Clean Data sheet references Raw Data, fills missing units with 0, salesperson with Unknown, recalculates Sales and Profit | C5: IF, cell references | D5: Raw Data includes a deliberate duplicate and missing values for practice.
A6: Summary tables | B6: Region, category and monthly sales summaries | C6: SUMIF, COUNTIF, SUMIFS, EDATE | D6: These are pivot-style summaries built with formulas.
A7: Advanced formulas | B7: Sales and profit calculations; filter-driven KPIs | C7: IF, SUMPRODUCT, SUMIF, SUMIFS | D7: VLOOKUP/INDEX-MATCH can be added if the instructor provides a lookup table.
A8: Visualization | B8: Region bar chart, category pie chart, monthly trend line chart | C8: Excel charts, conditional formatting | D8: Charts are linked to Analysis summary tables.
A9: Interactive controls | B9: Region and Category dropdowns on Dashboard | C9: Data Validation + SUMPRODUCT | D9: Dropdowns act as simple interactive filters. Native slicers/timeline need Excel PivotTables created in desktop Excel.
A10: Submission | B10: Save as YourName_ExcelDashboard.xlsx | C10: Save As | D10: Rename before submitting.
